README.rst
setup.py
onetoonemap/__init__.py
onetoonemap.egg-info/PKG-INFO
onetoonemap.egg-info/SOURCES.txt
onetoonemap.egg-info/dependency_links.txt
onetoonemap.egg-info/top_level.txt