Metadata-Version: 1.0
Name: onetoonemap
Version: 1.0.0
Summary: 1:1 mapping collection type
Home-page: https://github.com/cseelye/onetoonemap
Author: Carl Seelye
Author-email: cseelye@gmail.com
License: MIT
Keywords: 1:1 map dict
Platform: UNKNOWN
